kheiron/__init__.py
kheiron/constants.py
kheiron/early_stop.py
kheiron/opts.py
kheiron/trainer.py
kheiron/utils/__init__.py
kheiron/utils/logging.py
kheiron/utils/metrics.py
kheiron/utils/misc.py
kheiron/utils/optimizers.py
kheiron/utils/schedulers.py
kheiron/utils/statistics.py
Kheiron-1.0.4.dist-info/METADATA
Kheiron-1.0.4.dist-info/WHEEL
Kheiron-1.0.4.dist-info/top_level.txt
Kheiron-1.0.4.dist-info/RECORD
