Metadata-Version: 2.1
Name: Kheiron
Version: 1.0.4
Summary: Kheiron: Train and evaluate libary for Pytorch model.
Home-page: https://github.com/datnnt1997/Kheiron
Author: DatNgo
Author-email: datnnt97@gmail.com
License: MIT
Platform: UNKNOWN
Classifier: License :: OSI Approved :: MIT License
Classifier: Programming Language :: Python :: 3
Classifier: Programming Language :: Python :: 3.8
Requires-Dist: torch (~=1.12.1)
Requires-Dist: transformers (==4.21.2)
Requires-Dist: loguru (~=0.6.0)
Requires-Dist: jsonlines (~=3.1.0)
Requires-Dist: datasets (~=2.4.0)
Requires-Dist: tensorboard (~=2.10.0)
